rally_openstack/__init__.py
rally_openstack/_compat.py
rally_openstack/common/__init__.py
rally_openstack/common/consts.py
rally_openstack/common/credential.py
rally_openstack/common/exceptions.py
rally_openstack/common/osclients.py
rally_openstack/common/service.py
rally_openstack/common/validators.py
rally_openstack/common/cfg/__init__.py
rally_openstack/common/cfg/cinder.py
rally_openstack/common/cfg/cleanup.py
rally_openstack/common/cfg/glance.py
rally_openstack/common/cfg/heat.py
rally_openstack/common/cfg/ironic.py
rally_openstack/common/cfg/keystone_roles.py
rally_openstack/common/cfg/keystone_users.py
rally_openstack/common/cfg/magnum.py
rally_openstack/common/cfg/manila.py
rally_openstack/common/cfg/mistral.py
rally_openstack/common/cfg/monasca.py
rally_openstack/common/cfg/murano.py
rally_openstack/common/cfg/neutron.py
rally_openstack/common/cfg/nova.py
rally_openstack/common/cfg/octavia.py
rally_openstack/common/cfg/opts.py
rally_openstack/common/cfg/osclients.py
rally_openstack/common/cfg/profiler.py
rally_openstack/common/cfg/sahara.py
rally_openstack/common/cfg/senlin.py
rally_openstack/common/cfg/tempest.py
rally_openstack/common/cfg/vm.py
rally_openstack/common/cfg/watcher.py
rally_openstack/common/services/__init__.py
rally_openstack/common/services/gnocchi/__init__.py
rally_openstack/common/services/gnocchi/metric.py
rally_openstack/common/services/grafana/__init__.py
rally_openstack/common/services/grafana/grafana.py
rally_openstack/common/services/heat/__init__.py
rally_openstack/common/services/heat/main.py
rally_openstack/common/services/identity/__init__.py
rally_openstack/common/services/identity/identity.py
rally_openstack/common/services/identity/keystone_common.py
rally_openstack/common/services/identity/keystone_v2.py
rally_openstack/common/services/identity/keystone_v3.py
rally_openstack/common/services/image/__init__.py
rally_openstack/common/services/image/glance_common.py
rally_openstack/common/services/image/glance_v1.py
rally_openstack-3.0.0.dist-info/AUTHORS
rally_openstack-3.0.0.dist-info/LICENSE
rally_openstack-3.0.0.dist-info/METADATA
rally_openstack-3.0.0.dist-info/WHEEL
rally_openstack-3.0.0.dist-info/entry_points.txt
rally_openstack-3.0.0.dist-info/pbr.json
rally_openstack-3.0.0.dist-info/top_level.txt
rally_openstack-3.0.0.dist-info/RECORD
