Metadata-Version: 2.1
Name: rally-openstack
Version: 3.0.0
Summary: Rally plugins for OpenStack platform
Home-page: https://docs.openstack.org/rally/latest/
Author: OpenStack
Author-email: openstack-discuss@lists.openstack.org
License: Apache License, Version 2.0
Platform: UNKNOWN
Classifier: Environment :: OpenStack
Classifier: Intended Audience :: Developers
Classifier: Intended Audience :: Information Technology
Classifier: License :: OSI Approved :: Apache Software License
Classifier: Operating System :: POSIX :: Linux
Classifier: Programming Language :: Python
Classifier: Programming Language :: Python :: Implementation :: CPython
Classifier: Programming Language :: Python :: 3 :: Only
Classifier: Programming Language :: Python :: 3.8
Classifier: Programming Language :: Python :: 3.9
Classifier: Programming Language :: Python :: 3.10
Classifier: Programming Language :: Python :: 3.11
Requires-Python: >=3.8
Requires-Dist: gnocchiclient
Requires-Dist: keystoneauth1
Requires-Dist: kubernetes
Requires-Dist: os-faults (>=0.2.0)
Requires-Dist: osprofiler
Requires-Dist: python-barbicanclient
Requires-Dist: python-cinderclient (!=4.0.0)
Requires-Dist: python-designateclient
Requires-Dist: python-glanceclient
Requires-Dist: python-heatclient
Requires-Dist: python-ironicclient (!=2.5.2,!=2.7.1,!=3.0.0)
Requires-Dist: python-keystoneclient (!=2.1.0)
Requires-Dist: python-magnumclient
Requires-Dist: python-manilaclient
Requires-Dist: python-mistralclient (!=3.2.0)
Requires-Dist: python-monascaclient
Requires-Dist: python-muranoclient
Requires-Dist: python-neutronclient
Requires-Dist: python-novaclient
Requires-Dist: python-octaviaclient
Requires-Dist: python-saharaclient
Requires-Dist: python-senlinclient
Requires-Dist: python-swiftclient
Requires-Dist: python-troveclient
Requires-Dist: python-watcherclient
Requires-Dist: python-zaqarclient
Requires-Dist: rally (>=4.1.0)
Requires-Dist: requests (!=2.20.0,!=2.24.0)
